tai_keycloak/__init__.py
tai_keycloak/cli/commands/__init__.py
tai_keycloak/cli/commands/cmd_api/__init__.py
tai_keycloak/cli/commands/cmd_api/cmd_client/__init__.py
tai_keycloak/cli/commands/cmd_api/cmd_client/main.py
tai_keycloak/cli/commands/cmd_api/cmd_perm/__init__.py
tai_keycloak/cli/commands/cmd_api/cmd_perm/main.py
tai_keycloak/cli/commands/cmd_api/cmd_realm/__init__.py
tai_keycloak/cli/commands/cmd_api/cmd_realm/main.py
tai_keycloak/cli/commands/cmd_api/cmd_role/__init__.py
tai_keycloak/cli/commands/cmd_api/cmd_role/main.py
tai_keycloak/cli/commands/cmd_api/cmd_user/__init__.py
tai_keycloak/cli/commands/cmd_api/cmd_user/main.py
tai_keycloak/cli/commands/cmd_init/__init__.py
tai_keycloak/cli/commands/cmd_init/main.py
tai_keycloak/cli/commands/cmd_run/__init__.py
tai_keycloak/cli/commands/cmd_run/checks.py
tai_keycloak/cli/commands/cmd_run/display.py
tai_keycloak/cli/commands/cmd_run/docker_compose.py
tai_keycloak/cli/commands/cmd_run/main.py
tai_keycloak/cli/main.py
tai_keycloak/docker/.env.azure
tai_keycloak/docker/.env.development
tai_keycloak/docker/.env.example
tai_keycloak/docker/.env.onpremise
tai_keycloak/docker/.gitignore
tai_keycloak/docker/Dockerfile
tai_keycloak/docker/README.md
tai_keycloak/docker/docker-compose.yml
tai_keycloak/docker/main-realm.json
tai_keycloak/docker/traefik/certs/README.md
tai_keycloak/docker/traefik/dynamic/tls.yml
tai_keycloak/docker/workflows/GITHUB_SECRETS.md
tai_keycloak/docker/workflows/deploy-azure.yml
tai_keycloak/service/__init__.py
tai_keycloak/service/clients/__init__.py
tai_keycloak/service/clients/admin.py
tai_keycloak/service/clients/api/__init__.py
tai_keycloak/service/clients/api/asyn.py
tai_keycloak/service/clients/api/syn.py
tai_keycloak/service/clients/app.py
tai_keycloak/service/clients/config.py
tai_keycloak/service/clients/main.py
tai_keycloak/service/daos/__init__.py
tai_keycloak/service/daos/client.py
tai_keycloak/service/daos/client_roles.py
tai_keycloak/service/daos/group/__init__.py
tai_keycloak-0.2.5.dist-info/METADATA
tai_keycloak-0.2.5.dist-info/WHEEL
tai_keycloak-0.2.5.dist-info/entry_points.txt
tai_keycloak-0.2.5.dist-info/licenses/LICENSE
tai_keycloak-0.2.5.dist-info/RECORD
