Metadata-Version: 2.4
Name: tai-keycloak
Version: 0.2.5
Summary: 
License-File: LICENSE
Author: MateoSaezMata
Author-email: msaez@triplealpha.in
Requires-Python: >=3.10,<4.0
Classifier: Programming Language :: Python :: 3
Classifier: Programming Language :: Python :: 3.10
Classifier: Programming Language :: Python :: 3.11
Classifier: Programming Language :: Python :: 3.12
Classifier: Programming Language :: Python :: 3.13
Classifier: Programming Language :: Python :: 3.14
Provides-Extra: dev
Requires-Dist: click (>=8.3.0,<9.0.0)
Requires-Dist: pydantic (>=2.12.0,<3.0.0)
Requires-Dist: pydantic-settings (>=2.11.0,<3.0.0)
Requires-Dist: pytest (>=7.0.0) ; extra == "dev"
Requires-Dist: pytest-cov (>=4.0.0) ; extra == "dev"
Requires-Dist: pytest-mock (>=3.0.0) ; extra == "dev"
Requires-Dist: python-keycloak (>=5.8.1,<6.0.0)
Requires-Dist: rich (>=14.2.0,<15.0.0)
Requires-Dist: tai-alphi (>=2.0.1,<3.0.0)
